<?xml version="1.0" encoding="UTF-8" standalone="yes"?>
<unit xmlns="http://www.srcML.org/srcML/src" xmlns:cpp="http://www.srcML.org/srcML/cpp" revision="0.9.5" language="C++" filename="Data/Contest1245/all/29567655_63999338.cpp"><comment type="block" format="doxygen">/***********************************************
 *                   _ooOoo_                   *
 *                  o8888888o                  *
 *                  88" . "88                  *
 *                  (| -_- |)                  *
 *                  O\  =  /O                  *
 *               ____/`---'\____               *
 *             .'  \\|     |//  `.             *
 *            /  \\|||  :  |||//  \            *
 *           /  _||||| -:- |||||-  \           *
 *           |   | \\\  -   * |    |           *
 *           | \_|  ''\---/''  |   |           *
 *           \  .-\__  `-`  ___/-. /           *
 *         ___`. .'  /--.--\  `. . __          *
 *      ."" '&lt;  `.___\_&lt;|&gt;_/___.'  &gt;'"".       *
 *     | | :  `- \`.;`\ _ /`;.`/ - ` : | |     *
 *     \  \ `-.   \_ __\ /__ _/   .-` /  /     *
 *======`-.____`-.___\_____/___.-`____.-'======*
 *                   `=---='                   *
 *^^^^^^^^^^^^^^^^^^^^^^^^^^^^^^^^^^^^^^^^^^^^^^

             佛祖保佑       永无BUG

   本程序已经经过开光处理，绝无可能再产生bug
 **********************************************/</comment>
<cpp:include>#<cpp:directive>include</cpp:directive><cpp:file>&lt;algorithm&gt;</cpp:file></cpp:include>
<cpp:include>#<cpp:directive>include</cpp:directive> <cpp:file>&lt;iostream&gt;</cpp:file></cpp:include>
<cpp:include>#<cpp:directive>include</cpp:directive>  <cpp:file>&lt;cstdlib&gt;</cpp:file></cpp:include>
<cpp:include>#<cpp:directive>include</cpp:directive>  <cpp:file>&lt;cstring&gt;</cpp:file></cpp:include>
<cpp:include>#<cpp:directive>include</cpp:directive>   <cpp:file>&lt;string&gt;</cpp:file></cpp:include>
<cpp:include>#<cpp:directive>include</cpp:directive>   <cpp:file>&lt;vector&gt;</cpp:file></cpp:include>
<cpp:include>#<cpp:directive>include</cpp:directive>   <cpp:file>&lt;cstdio&gt;</cpp:file></cpp:include>
<cpp:include>#<cpp:directive>include</cpp:directive>    <cpp:file>&lt;queue&gt;</cpp:file></cpp:include>
<cpp:include>#<cpp:directive>include</cpp:directive>    <cpp:file>&lt;stack&gt;</cpp:file></cpp:include>
<cpp:include>#<cpp:directive>include</cpp:directive>    <cpp:file>&lt;ctime&gt;</cpp:file></cpp:include>
<cpp:include>#<cpp:directive>include</cpp:directive>    <cpp:file>&lt;cmath&gt;</cpp:file></cpp:include>
<cpp:include>#<cpp:directive>include</cpp:directive>      <cpp:file>&lt;map&gt;</cpp:file></cpp:include>
<cpp:include>#<cpp:directive>include</cpp:directive>      <cpp:file>&lt;set&gt;</cpp:file></cpp:include>
<cpp:define>#<cpp:directive>define</cpp:directive> <cpp:macro><name>ll</name></cpp:macro> <cpp:value>long long</cpp:value></cpp:define>
<cpp:define>#<cpp:directive>define</cpp:directive> <cpp:macro><name>inf</name></cpp:macro> <cpp:value>0x3f3f3f3f</cpp:value></cpp:define>
<cpp:define>#<cpp:directive>define</cpp:directive> <cpp:macro><name>pii</name></cpp:macro> <cpp:value>pair&lt;int,int&gt;</cpp:value></cpp:define>
<cpp:define>#<cpp:directive>define</cpp:directive> <cpp:macro><name>INF</name></cpp:macro> <cpp:value>0x3f3f3f3f3f3f3f3f</cpp:value></cpp:define>
<cpp:define>#<cpp:directive>define</cpp:directive> <cpp:macro><name>mkp</name><parameter_list>(<parameter><type><name>a</name></type></parameter>,<parameter><type><name>b</name></type></parameter>)</parameter_list></cpp:macro> <cpp:value>make_pair(a,b)</cpp:value></cpp:define>
<cpp:define>#<cpp:directive>define</cpp:directive> <cpp:macro><name>FOR</name><parameter_list>(<parameter><type><name>i</name></type></parameter>,<parameter><type><name>a</name></type></parameter>,<parameter><type><name>b</name></type></parameter>)</parameter_list></cpp:macro> <cpp:value>for(int i=a;i&lt;b;i++)</cpp:value></cpp:define>
<cpp:define>#<cpp:directive>define</cpp:directive> <cpp:macro><name>db1</name><parameter_list>(<parameter><type><name>x</name></type></parameter>)</parameter_list></cpp:macro> <cpp:value>cout&lt;&lt;#x&lt;&lt;"="&lt;&lt;(x)&lt;&lt;endl</cpp:value></cpp:define>
<cpp:define>#<cpp:directive>define</cpp:directive> <cpp:macro><name>db2</name><parameter_list>(<parameter><type><name>x</name></type></parameter>,<parameter><type><name>y</name></type></parameter>)</parameter_list></cpp:macro> <cpp:value>cout&lt;&lt;#x&lt;&lt;"="&lt;&lt;(x)&lt;&lt;", "&lt;&lt;#y&lt;&lt;"="&lt;&lt;(y)&lt;&lt;endl</cpp:value></cpp:define>
<cpp:define>#<cpp:directive>define</cpp:directive> <cpp:macro><name>db3</name><parameter_list>(<parameter><type><name>x</name></type></parameter>,<parameter><type><name>y</name></type></parameter>,<parameter><type><name>z</name></type></parameter>)</parameter_list></cpp:macro> <cpp:value>cout&lt;&lt;#x&lt;&lt;"="&lt;&lt;(x)&lt;&lt;", "&lt;&lt;#y&lt;&lt;"="&lt;&lt;(y)&lt;&lt;", "&lt;&lt;#z&lt;&lt;"="&lt;&lt;(z)&lt;&lt;endl</cpp:value></cpp:define>
<cpp:define>#<cpp:directive>define</cpp:directive> <cpp:macro><name>getchar</name><parameter_list>()</parameter_list></cpp:macro><cpp:value>(p1==p2&amp;&amp;(p2=(p1=buf)+fread(buf,1,1&lt;&lt;22,stdin),p1==p2)?EOF:*p1++)</cpp:value></cpp:define>
<using>using <namespace>namespace <name>std</name>;</namespace></using>
<decl_stmt><decl><type><name>char</name></type> <name><name>buf</name><index>[<expr><operator>(</operator><literal type="number">1</literal><operator>&lt;&lt;</operator><literal type="number">22</literal><operator>)</operator></expr>]</index></name></decl>,<modifier>*</modifier><decl><type ref="prev"/><name>p1</name><init>=<expr><name>buf</name></expr></init></decl>,<modifier>*</modifier><decl><type ref="prev"/><name>p2</name><init>=<expr><name>buf</name></expr></init></decl>;</decl_stmt>
<function><specifier>inline</specifier> <type><name>ll</name></type> <name>read</name><parameter_list>()</parameter_list><block>{
    <decl_stmt><decl><type><name>char</name></type> <name>c</name><init>=<expr><call><name>getchar</name><argument_list>()</argument_list></call></expr></init></decl>;</decl_stmt><decl_stmt><decl><type><name>ll</name></type> <name>x</name><init>=<expr><literal type="number">0</literal></expr></init></decl>,<decl><type ref="prev"/><name>f</name><init>=<expr><literal type="number">1</literal></expr></init></decl>;</decl_stmt>
    <while>while<condition>(<expr><name><name>c</name><argument_list type="generic">&lt;<argument><expr><literal type="char">'0'</literal><operator>||</operator><name>c</name></expr></argument>&gt;</argument_list></name><literal type="char">'9'</literal></expr>)</condition><block>{<if>if<condition>(<expr><name>c</name><operator>==</operator><literal type="char">'-'</literal></expr>)</condition><then><block type="pseudo"><expr_stmt><expr><name>f</name><operator>=</operator><operator>-</operator><literal type="number">1</literal></expr>;</expr_stmt></block></then></if><expr_stmt><expr><name>c</name><operator>=</operator><call><name>getchar</name><argument_list>()</argument_list></call></expr>;</expr_stmt>}</block></while>
    <while>while<condition>(<expr><name>c</name><operator>&gt;=</operator><literal type="char">'0'</literal><operator>&amp;&amp;</operator><name>c</name><operator>&lt;=</operator><literal type="char">'9'</literal></expr>)</condition><block type="pseudo"><expr_stmt><expr><name>x</name><operator>=</operator><name>x</name><operator>*</operator><literal type="number">10</literal><operator>+</operator><name>c</name><operator>-</operator><literal type="char">'0'</literal></expr><operator>,</operator><expr><name>c</name><operator>=</operator><call><name>getchar</name><argument_list>()</argument_list></call></expr>;</expr_stmt></block></while>
    <return>return <expr><name>x</name><operator>*</operator><name>f</name></expr>;</return>
}</block></function>
<decl_stmt><decl><type><specifier>const</specifier> <name>int</name></type> <name>maxn</name><init>=<expr><literal type="number">4005</literal></expr></init></decl>;</decl_stmt>
<function><type><name>int</name></type> <name>gcd</name><parameter_list>(<parameter><decl><type><name>int</name></type> <name>a</name></decl></parameter>,<parameter><decl><type><name>int</name></type> <name>b</name></decl></parameter>)</parameter_list><block>{<return>return <expr><ternary><condition><expr><operator>!</operator><name>b</name></expr>?</condition><then><expr><name>a</name></expr></then><else>:<expr><call><name>gcd</name><argument_list>(<argument><expr><name>b</name></expr></argument>,<argument><expr><name>a</name><operator>%</operator><name>b</name></expr></argument>)</argument_list></call></expr></else></ternary></expr>;</return>}</block></function>
<function><type><name>int</name></type> <name>main</name><parameter_list>()</parameter_list><block>{
    <cpp:ifdef>#<cpp:directive>ifdef</cpp:directive> <name>DanDan</name></cpp:ifdef>
    <expr_stmt><expr><call><name>freopen</name><argument_list>(<argument><expr><literal type="string">"in.txt"</literal></expr></argument>,<argument><expr><literal type="string">"r"</literal></expr></argument>,<argument><expr><name>stdin</name></expr></argument>)</argument_list></call></expr>;</expr_stmt>
    <comment type="line">//freopen("in.txt","w",stdout);</comment>
    <decl_stmt><decl><type><name>clock_t</name></type> <name>start</name><init>=<expr><call><name>clock</name><argument_list>()</argument_list></call></expr></init></decl>;</decl_stmt>
    <cpp:endif>#<cpp:directive>endif</cpp:directive></cpp:endif> <comment type="line">//DanDan</comment>
    <decl_stmt><decl><type><name>int</name></type> <name>t</name><init>=<expr><call><name>read</name><argument_list>()</argument_list></call></expr></init></decl>;</decl_stmt>
    <while>while<condition>(<expr><name>t</name><operator>--</operator></expr>)</condition><block>{
        <decl_stmt><decl><type><name>int</name></type> <name>a</name><init>=<expr><call><name>read</name><argument_list>()</argument_list></call></expr></init></decl>,<decl><type ref="prev"/><name>b</name><init>=<expr><call><name>read</name><argument_list>()</argument_list></call></expr></init></decl>;</decl_stmt>
        <if>if<condition>(<expr><name>a</name><operator>==</operator><literal type="number">1</literal></expr>)</condition><then><block>{<expr_stmt><expr><call><name>printf</name><argument_list>(<argument><expr><literal type="string">"Finite\n"</literal></expr></argument>)</argument_list></call></expr>;</expr_stmt><continue>continue;</continue>}</block></then></if>
        <if>if<condition>(<expr><name>a</name><operator>==</operator><name>b</name></expr>)</condition><then><block>{<expr_stmt><expr><call><name>printf</name><argument_list>(<argument><expr><literal type="string">"Infinite\n"</literal></expr></argument>)</argument_list></call></expr>;</expr_stmt><continue>continue;</continue>}</block></then></if>
        <if>if<condition>(<expr><call><name>gcd</name><argument_list>(<argument><expr><name>a</name></expr></argument>,<argument><expr><name>b</name></expr></argument>)</argument_list></call><operator>==</operator><literal type="number">1</literal></expr>)</condition><then><block>{<expr_stmt><expr><call><name>printf</name><argument_list>(<argument><expr><literal type="string">"Finite\n"</literal></expr></argument>)</argument_list></call></expr>;</expr_stmt>}</block></then>
        <else>else <block>{<expr_stmt><expr><call><name>printf</name><argument_list>(<argument><expr><literal type="string">"Infinite\n"</literal></expr></argument>)</argument_list></call></expr>;</expr_stmt>}</block></else></if>
    }</block></while>

    <cpp:ifdef>#<cpp:directive>ifdef</cpp:directive> <name>DanDan</name></cpp:ifdef>
    <decl_stmt><decl><type><name>clockid_t</name></type> <name>end</name><init>=<expr><call><name>clock</name><argument_list>()</argument_list></call></expr></init></decl>;</decl_stmt>
    <decl_stmt><decl><type><name>double</name></type> <name>endtime</name><init>=<expr><call>(<name>double</name>)<argument_list>(<argument><expr><name>end</name><operator>-</operator><name>start</name></expr></argument>)</argument_list></call><operator>/</operator><name>CLOCKS_PER_SEC</name></expr></init></decl>;</decl_stmt>
    <expr_stmt><expr><call><name>printf</name><argument_list>(<argument><expr><literal type="string">"\n\n\n\n\n"</literal></expr></argument>)</argument_list></call></expr>;</expr_stmt>
    <expr_stmt><expr><name>cout</name><operator>&lt;&lt;</operator><literal type="string">"Total time:"</literal><operator>&lt;&lt;</operator><name>endtime</name><operator>&lt;&lt;</operator><literal type="string">"s"</literal><operator>&lt;&lt;</operator><name>endl</name></expr>;</expr_stmt>        <comment type="line">//s为单位</comment>
    <expr_stmt><expr><name>cout</name><operator>&lt;&lt;</operator><literal type="string">"Total time:"</literal><operator>&lt;&lt;</operator><name>endtime</name><operator>*</operator><literal type="number">1000</literal><operator>&lt;&lt;</operator><literal type="string">"ms"</literal><operator>&lt;&lt;</operator><name>endl</name></expr>;</expr_stmt>    <comment type="line">//ms为单位</comment>
    <cpp:endif>#<cpp:directive>endif</cpp:directive></cpp:endif> <comment type="line">//DanDan</comment>
    <return>return <expr><literal type="number">0</literal></expr>;</return>
}</block></function>


<comment type="line">// ━━━━━━神兽出没━━━━━━</comment>
<comment type="line">//      ┏┓       ┏┓</comment>
<comment type="line">//     ┏┛┻━━━━━━━┛┻┓</comment>
<comment type="line">//     ┃           ┃</comment>
<comment type="line">//     ┃     ━     ┃</comment>
<comment type="line">//     ????━????   ┃</comment>
<comment type="line">//     ┃           ┃</comment>
<comment type="line">//     ┃    ┻      ┃</comment>
<comment type="line">//     ┃           ┃</comment>
<comment type="line">//     ┗━┓       ┏━┛</comment>
<comment type="line">//       ┃       ┃</comment>
<comment type="line">//       ┃       ┃</comment>
<comment type="line">//       ┃       ┗━━━┓</comment>
<comment type="line">//       ┃           ┣┓</comment>
<comment type="line">//       ┃           ┏┛</comment>
<comment type="line">//       ┗┓┓┏━━━━━┳┓┏┛</comment>
<comment type="line">//        ┃┫┫     ┃┫┫</comment>
<comment type="line">//        ┗┻┛     ┗┻┛</comment>
<comment type="line">//</comment>
<comment type="line">// ━━━━━━感觉萌萌哒━━━━━━</comment>

</unit>
