<?xml version="1.0" encoding="UTF-8" standalone="yes"?>
<unit xmlns="http://www.srcML.org/srcML/src" xmlns:cpp="http://www.srcML.org/srcML/cpp" revision="0.9.5" language="C++" filename="Data/Contest1244/all/28909307_62465347.cpp"><cpp:include>#<cpp:directive>include</cpp:directive><cpp:file>&lt;bits/stdc++.h&gt;</cpp:file></cpp:include>
<cpp:define>#<cpp:directive>define</cpp:directive> <cpp:macro><name>MAX_N</name></cpp:macro> <cpp:value>8005</cpp:value></cpp:define>
<cpp:define>#<cpp:directive>define</cpp:directive> <cpp:macro><name>MAX_M</name></cpp:macro> <cpp:value>55</cpp:value></cpp:define>
<cpp:define>#<cpp:directive>define</cpp:directive> <cpp:macro><name>pb</name></cpp:macro> <cpp:value>push_back</cpp:value></cpp:define>
<cpp:define>#<cpp:directive>define</cpp:directive> <cpp:macro><name>eb</name></cpp:macro> <cpp:value>emplace_back</cpp:value></cpp:define>
<cpp:define>#<cpp:directive>define</cpp:directive> <cpp:macro><name>mp</name></cpp:macro> <cpp:value>make_pair</cpp:value></cpp:define>
<cpp:define>#<cpp:directive>define</cpp:directive> <cpp:macro><name>all</name><parameter_list>(<parameter><type><name>V</name></type></parameter>)</parameter_list></cpp:macro> <cpp:value>(V).begin(),(V).end()</cpp:value></cpp:define>
<cpp:define>#<cpp:directive>define</cpp:directive> <cpp:macro><name>reset</name><parameter_list>(<parameter><type><name>V</name></type></parameter>)</parameter_list></cpp:macro> <cpp:value>(V).clear();(V).resize(0);</cpp:value></cpp:define>
<cpp:define>#<cpp:directive>define</cpp:directive> <cpp:macro><name>sq</name><parameter_list>(<parameter><type><name>x</name></type></parameter>)</parameter_list></cpp:macro> <cpp:value>((x)*(x))</cpp:value></cpp:define>
<cpp:define>#<cpp:directive>define</cpp:directive> <cpp:macro><name>abs</name><parameter_list>(<parameter><type><name>x</name></type></parameter>)</parameter_list></cpp:macro> <cpp:value>((x)&gt;0?(x):(-(x)))</cpp:value></cpp:define>
<cpp:define>#<cpp:directive>define</cpp:directive> <cpp:macro><name>fi</name></cpp:macro> <cpp:value>first</cpp:value></cpp:define>
<cpp:define>#<cpp:directive>define</cpp:directive> <cpp:macro><name>se</name></cpp:macro> <cpp:value>second</cpp:value></cpp:define>
<cpp:define>#<cpp:directive>define</cpp:directive> <cpp:macro><name>LL_inf</name></cpp:macro> <cpp:value>(1LL&lt;&lt;40)</cpp:value></cpp:define>
<cpp:define>#<cpp:directive>define</cpp:directive> <cpp:macro><name>full_inf</name></cpp:macro> <cpp:value>0x7fffffff</cpp:value></cpp:define>
<cpp:define>#<cpp:directive>define</cpp:directive> <cpp:macro><name>half_inf</name></cpp:macro> <cpp:value>0x3fffffff</cpp:value></cpp:define>
<cpp:define>#<cpp:directive>define</cpp:directive> <cpp:macro><name>inf</name></cpp:macro> <cpp:value>0x3fffffff</cpp:value></cpp:define>
<cpp:define>#<cpp:directive>define</cpp:directive> <cpp:macro><name>MOD</name></cpp:macro> <cpp:value>1000000007</cpp:value></cpp:define>
<cpp:define>#<cpp:directive>define</cpp:directive> <cpp:macro><name>cpx_mod</name><parameter_list>(<parameter><type><name>x</name></type></parameter>)</parameter_list></cpp:macro> <cpp:value>(((LD)(((LL)x.real())%MOD)),((LD)(((LL)x.imag())%MOD)))</cpp:value></cpp:define>
<using>using <namespace>namespace <name>std</name>;</namespace></using>
<typedef>typedef <type><name>long</name> <name>long</name></type> <name>LL</name>;</typedef>
<typedef>typedef <type><name>long</name> <name>double</name></type> <name>LD</name>;</typedef>
<typedef>typedef <type><name><name>pair</name><argument_list type="generic">&lt;<argument><expr><name>int</name></expr></argument>,<argument><expr><name>int</name></expr></argument>&gt;</argument_list></name></type> <name>pii</name>;</typedef>
<typedef>typedef <type><name><name>pair</name><argument_list type="generic">&lt;<argument><expr><name>LL</name></expr></argument>,<argument><expr><name>LL</name></expr></argument>&gt;</argument_list></name></type> <name>pil</name>;</typedef>
<typedef>typedef <type><name><name>pair</name><argument_list type="generic">&lt;<argument><expr><name>LL</name></expr></argument>,<argument><expr><name>string</name></expr></argument>&gt;</argument_list></name></type> <name>pls</name>;</typedef>
<typedef>typedef <type><name><name>complex</name><argument_list type="generic">&lt;<argument><expr><name>LD</name></expr></argument>&gt;</argument_list></name></type> <name>Complex</name>;</typedef>
<typedef>typedef <type><name>long</name> <name>double</name></type> <name>LD</name>;</typedef>
<function><type><name>int</name></type> <name>main</name><parameter_list>()</parameter_list><block>{
	<decl_stmt><decl><type><name>int</name></type> <name>a</name></decl>,<decl><type ref="prev"/><name>b</name></decl>,<decl><type ref="prev"/><name>c</name></decl>,<decl><type ref="prev"/><name>d</name></decl>,<decl><type ref="prev"/><name>k</name></decl>,<decl><type ref="prev"/><name>T</name></decl>;</decl_stmt>
	<expr_stmt><expr><call><name>scanf</name><argument_list>(<argument><expr><literal type="string">"%d"</literal></expr></argument>,<argument><expr><operator>&amp;</operator><name>T</name></expr></argument>)</argument_list></call></expr>;</expr_stmt>

	<while>while<condition>(<expr><name>T</name><operator>--</operator></expr>)</condition><block>{
		<expr_stmt><expr><call><name>scanf</name><argument_list>(<argument><expr><literal type="string">"%d %d %d %d %d"</literal></expr></argument>,<argument><expr><operator>&amp;</operator><name>a</name></expr></argument>,<argument><expr><operator>&amp;</operator><name>b</name></expr></argument>,<argument><expr><operator>&amp;</operator><name>c</name></expr></argument>,<argument><expr><operator>&amp;</operator><name>d</name></expr></argument>,<argument><expr><operator>&amp;</operator><name>k</name></expr></argument>)</argument_list></call></expr>;</expr_stmt>
		<decl_stmt><decl><type><name>int</name></type> <name>x</name> <init>= <expr><name>a</name><operator>/</operator><name>c</name> <operator>+</operator> <operator>(</operator><ternary><condition><expr><name>a</name><operator>%</operator><name>c</name></expr> ?</condition><then> <expr><literal type="number">1</literal></expr> </then><else>: <expr><literal type="number">0</literal></expr></else></ternary><operator>)</operator></expr></init></decl>;</decl_stmt>
		<decl_stmt><decl><type><name>int</name></type> <name>y</name> <init>= <expr><name>b</name><operator>/</operator><name>d</name> <operator>+</operator> <operator>(</operator><ternary><condition><expr><name>b</name><operator>%</operator><name>d</name></expr> ?</condition><then> <expr><literal type="number">1</literal></expr> </then><else>: <expr><literal type="number">0</literal></expr></else></ternary><operator>)</operator></expr></init></decl>;</decl_stmt>
		<if>if<condition>(<expr><name>x</name><operator>+</operator><name>y</name><operator>&gt;</operator><name>k</name></expr>)</condition><then>	<block type="pseudo"><expr_stmt><expr><call><name>printf</name><argument_list>(<argument><expr><literal type="string">"-1\n"</literal></expr></argument>)</argument_list></call></expr>;</expr_stmt></block></then>
		<else>else	<block type="pseudo"><expr_stmt><expr><call><name>printf</name><argument_list>(<argument><expr><literal type="string">"%d %d\n"</literal></expr></argument>,<argument><expr><name>x</name></expr></argument>,<argument><expr><name>y</name></expr></argument>)</argument_list></call></expr>;</expr_stmt></block></else></if>
	}</block></while>
	<return>return <expr><literal type="number">0</literal></expr>;</return>
}</block></function></unit>
