<?xml version="1.0" encoding="UTF-8" standalone="yes"?>
<unit xmlns="http://www.srcML.org/srcML/src" xmlns:cpp="http://www.srcML.org/srcML/cpp" revision="0.9.5" language="C++" filename="Data/Contest1248/all/29178396_62983535.cpp"><cpp:include>#<cpp:directive>include</cpp:directive> <cpp:file>&lt;bits/stdc++.h&gt;</cpp:file></cpp:include>

<using>using <namespace>namespace <name>std</name>;</namespace></using>

<typedef>typedef <type><name><name>pair</name><argument_list type="generic">&lt;<argument><expr><name>int</name></expr></argument>,<argument><expr><name>int</name></expr></argument>&gt;</argument_list></name></type> <name>pii</name>;</typedef>
<typedef>typedef <type><name>long</name> <name>long</name></type> <name>ll</name>;</typedef>

<function><template>template<parameter_list>&lt;<parameter><type><name>class</name></type> <name>T</name></parameter>&gt;</parameter_list></template><type><name>void</name></type> <name>byebye</name><parameter_list>(<parameter><decl><type><name>T</name></type> <name>_rpl</name></decl></parameter>)</parameter_list><block>{<expr_stmt><expr><name>cout</name><operator>&lt;&lt;</operator><name>_rpl</name><operator>&lt;&lt;</operator><name>endl</name></expr>;</expr_stmt><expr_stmt><expr><call><name>exit</name><argument_list>(<argument><expr><literal type="number">0</literal></expr></argument>)</argument_list></call></expr>;</expr_stmt>}</block></function>
<function><type><name>int</name></type> <name>nextint</name><parameter_list>()</parameter_list><block>{<decl_stmt><decl><type><name>int</name></type> <name>x</name></decl>;</decl_stmt><expr_stmt><expr><call><name>scanf</name><argument_list>(<argument><expr><literal type="string">"%d"</literal></expr></argument>,<argument><expr><operator>&amp;</operator><name>x</name></expr></argument>)</argument_list></call></expr>;</expr_stmt><return>return <expr><name>x</name></expr>;</return>}</block></function>
<function><type><name>ll</name></type> <name>nextll</name><parameter_list>()</parameter_list><block>{<decl_stmt><decl><type><name>ll</name></type> <name>x</name></decl>;</decl_stmt><expr_stmt><expr><call><name>scanf</name><argument_list>(<argument><expr><literal type="string">"%lld"</literal></expr></argument>,<argument><expr><operator>&amp;</operator><name>x</name></expr></argument>)</argument_list></call></expr>;</expr_stmt><return>return <expr><name>x</name></expr>;</return>}</block></function>

<function><type><name>int</name></type> <name>read</name><parameter_list>()</parameter_list><block>{
	<decl_stmt><decl><type><name>int</name></type> <name>f</name><init>=<expr><literal type="number">1</literal></expr></init></decl>,<decl><type ref="prev"/><name>ret</name><init>=<expr><literal type="number">0</literal></expr></init></decl>;</decl_stmt>
	<decl_stmt><decl><type><name>char</name></type> <name>c</name><init>=<expr><call><name>getchar</name><argument_list>()</argument_list></call></expr></init></decl>;</decl_stmt>
	<while>while<condition>(<expr><name><name>c</name><argument_list type="generic">&lt;<argument><expr><literal type="char">'0'</literal><operator>||</operator><name>c</name></expr></argument>&gt;</argument_list></name><literal type="char">'9'</literal></expr>)</condition><block>{<if>if<condition>(<expr><name>c</name><operator>==</operator><literal type="char">'-'</literal></expr>)</condition><then><block type="pseudo"><expr_stmt><expr><name>f</name><operator>=</operator><operator>-</operator><literal type="number">1</literal></expr>;</expr_stmt></block></then></if><expr_stmt><expr><name>c</name><operator>=</operator><call><name>getchar</name><argument_list>()</argument_list></call></expr>;</expr_stmt>}</block></while>
	<while>while<condition>(<expr><name>c</name><operator>&gt;=</operator><literal type="char">'0'</literal><operator>&amp;&amp;</operator><name>c</name><operator>&lt;=</operator><literal type="char">'9'</literal></expr>)</condition><block>{<expr_stmt><expr><name>ret</name><operator>=</operator><name>ret</name><operator>*</operator><literal type="number">10</literal><operator>+</operator><operator>(</operator><name>c</name><operator>-</operator><literal type="char">'0'</literal><operator>)</operator></expr>;</expr_stmt><expr_stmt><expr><name>c</name><operator>=</operator><call><name>getchar</name><argument_list>()</argument_list></call></expr>;</expr_stmt>}</block></while>
	<return>return <expr><name>ret</name><operator>*</operator><name>f</name></expr>;</return>
}</block></function>

<decl_stmt><decl><type><name>int</name></type> <name>n</name></decl>;</decl_stmt>
<decl_stmt><decl><type><name>int</name></type> <name><name>a</name><index>[<expr><literal type="number">100005</literal></expr>]</index></name></decl>;</decl_stmt>
<decl_stmt><decl><type><name>ll</name></type> <name>ans1</name></decl>,<decl><type ref="prev"/><name>ans2</name></decl>;</decl_stmt>

<function><type><name>int</name></type> <name>main</name><parameter_list>()</parameter_list><block>{
	<expr_stmt><expr><call><name>scanf</name><argument_list>(<argument><expr><literal type="string">"%d"</literal></expr></argument>,<argument><expr><operator>&amp;</operator><name>n</name></expr></argument>)</argument_list></call></expr>;</expr_stmt>
	<for>for<control>(<init><decl><type><name>int</name></type> <name>i</name><init>=<expr><literal type="number">0</literal></expr></init></decl>;</init><condition><expr><name>i</name><operator>&lt;</operator><name>n</name></expr>;</condition><incr><expr><operator>++</operator><name>i</name></expr></incr>)</control><block type="pseudo"><expr_stmt><expr><call><name>scanf</name><argument_list>(<argument><expr><literal type="string">"%d"</literal></expr></argument>,<argument><expr><name>a</name><operator>+</operator><name>i</name></expr></argument>)</argument_list></call></expr>;</expr_stmt></block></for>
	<expr_stmt><expr><call><name>sort</name><argument_list>(<argument><expr><name>a</name></expr></argument>,<argument><expr><name>a</name><operator>+</operator><name>n</name></expr></argument>)</argument_list></call></expr>;</expr_stmt>
	<if>if<condition>(<expr><name>n</name><operator>&amp;</operator><literal type="number">1</literal></expr>)</condition><then><block>{
		<decl_stmt><decl><type><name>ll</name></type> <name>sum</name><init>=<expr><literal type="number">0</literal></expr></init></decl>,<decl><type ref="prev"/><name>sum2</name><init>=<expr><literal type="number">0</literal></expr></init></decl>;</decl_stmt>
		<for>for<control>(<init><decl><type><name>int</name></type> <name>i</name><init>=<expr><literal type="number">0</literal></expr></init></decl>;</init><condition><expr><name>i</name><operator>&lt;</operator><name>n</name></expr>;</condition><incr><expr><operator>++</operator><name>i</name></expr></incr>)</control><block>{
			<expr_stmt><expr><name>sum</name><operator>+=</operator><name><name>a</name><index>[<expr><name>i</name></expr>]</index></name></expr>;</expr_stmt>
		}</block></for>
		<for>for<control>(<init><decl><type><name>int</name></type> <name>i</name><init>=<expr><literal type="number">0</literal></expr></init></decl>;</init><condition><expr><name>i</name><operator>&lt;</operator><name>n</name><operator>/</operator><literal type="number">2</literal></expr>;</condition><incr><expr><operator>++</operator><name>i</name></expr></incr>)</control><block type="pseudo"><expr_stmt><expr><name>sum2</name><operator>+=</operator><name><name>a</name><index>[<expr><name>i</name></expr>]</index></name></expr>;</expr_stmt></block></for>
		<expr_stmt><expr><name>ans1</name><operator>=</operator><name>sum2</name><operator>*</operator><name>sum2</name><operator>+</operator><operator>(</operator><name>sum</name><operator>-</operator><name>sum2</name><operator>)</operator><operator>*</operator><operator>(</operator><name>sum</name><operator>-</operator><name>sum2</name><operator>)</operator></expr>;</expr_stmt>
		<expr_stmt><expr><name>sum2</name><operator>+=</operator><name><name>a</name><index>[<expr><name>n</name><operator>/</operator><literal type="number">2</literal></expr>]</index></name></expr>;</expr_stmt>
		<expr_stmt><expr><name>ans2</name><operator>=</operator><name>sum2</name><operator>*</operator><name>sum2</name><operator>+</operator><operator>(</operator><name>sum</name><operator>-</operator><name>sum2</name><operator>)</operator><operator>*</operator><operator>(</operator><name>sum</name><operator>-</operator><name>sum2</name><operator>)</operator></expr>;</expr_stmt>
		<expr_stmt><expr><call><name>printf</name><argument_list>(<argument><expr><literal type="string">"%lld\n"</literal></expr></argument>,<argument><expr><call><name>max</name><argument_list>(<argument><expr><name>ans1</name></expr></argument>,<argument><expr><name>ans2</name></expr></argument>)</argument_list></call></expr></argument>)</argument_list></call></expr>;</expr_stmt>
	}</block></then>
	<else>else<block>{
		<decl_stmt><decl><type><name>ll</name></type> <name>sum</name><init>=<expr><literal type="number">0</literal></expr></init></decl>,<decl><type ref="prev"/><name>sum2</name><init>=<expr><literal type="number">0</literal></expr></init></decl>;</decl_stmt>
		<for>for<control>(<init><decl><type><name>int</name></type> <name>i</name><init>=<expr><literal type="number">0</literal></expr></init></decl>;</init><condition><expr><name>i</name><operator>&lt;</operator><name>n</name></expr>;</condition><incr><expr><operator>++</operator><name>i</name></expr></incr>)</control><block>{
			<expr_stmt><expr><name>sum</name><operator>+=</operator><name><name>a</name><index>[<expr><name>i</name></expr>]</index></name></expr>;</expr_stmt>
		}</block></for>
		<for>for<control>(<init><decl><type><name>int</name></type> <name>i</name><init>=<expr><literal type="number">0</literal></expr></init></decl>;</init><condition><expr><name>i</name><operator>&lt;</operator><name>n</name><operator>/</operator><literal type="number">2</literal></expr>;</condition><incr><expr><operator>++</operator><name>i</name></expr></incr>)</control><block type="pseudo"><expr_stmt><expr><name>sum2</name><operator>+=</operator><name><name>a</name><index>[<expr><name>i</name></expr>]</index></name></expr>;</expr_stmt></block></for>
		<expr_stmt><expr><name>ans1</name><operator>=</operator><name>sum2</name><operator>*</operator><name>sum2</name><operator>+</operator><operator>(</operator><name>sum</name><operator>-</operator><name>sum2</name><operator>)</operator><operator>*</operator><operator>(</operator><name>sum</name><operator>-</operator><name>sum2</name><operator>)</operator></expr>;</expr_stmt>
		<expr_stmt><expr><call><name>printf</name><argument_list>(<argument><expr><literal type="string">"%lld\n"</literal></expr></argument>,<argument><expr><name>ans1</name></expr></argument>)</argument_list></call></expr>;</expr_stmt>
	}</block></else></if>
	<return>return <expr><literal type="number">0</literal></expr>;</return>
}</block></function>
</unit>
